sinapsis_dfine/__init__.py
sinapsis_dfine/helpers/__init__.py
sinapsis_dfine/helpers/dataset_utils.py
sinapsis_dfine/helpers/env_var_keys.py
sinapsis_dfine/helpers/metrics.py
sinapsis_dfine/helpers/schemas.py
sinapsis_dfine/helpers/tags.py
sinapsis_dfine/templates/__init__.py
sinapsis_dfine/templates/dfine_base.py
sinapsis_dfine/templates/dfine_inference.py
sinapsis_dfine/templates/dfine_training.py
sinapsis_dfine-0.2.0.dist-info/licenses/LICENSE
sinapsis_dfine-0.2.0.dist-info/METADATA
sinapsis_dfine-0.2.0.dist-info/WHEEL
sinapsis_dfine-0.2.0.dist-info/top_level.txt
sinapsis_dfine-0.2.0.dist-info/RECORD
