Metadata-Version: 2.4
Name: sinapsis-dfine
Version: 0.2.0
Summary: Training and inference templates based on the D-FINE architecture.
Author-email: SinapsisAI <dev@sinapsis.tech>
Project-URL: Homepage, https://sinapsis.tech
Project-URL: Documentation, https://docs.sinapsis.tech/docs
Project-URL: Tutorials, https://docs.sinapsis.tech/tutorials
Project-URL: Repository, https://github.com/Sinapsis-AI/sinapsis-object-detection.git
Requires-Python: >=3.10
License-File: LICENSE
Requires-Dist: datasets>=4.2.0
Requires-Dist: sinapsis>=0.1.1
Requires-Dist: sinapsis-data-visualization>=0.1.12
Requires-Dist: sinapsis-generic-data-tools>=0.1.1
Requires-Dist: torch>=2.8.0
Requires-Dist: torchmetrics>=1.8.2
Requires-Dist: transformers[accelerate,hf-xet]>=4.56.1
Provides-Extra: sinapsis-data-readers
Requires-Dist: sinapsis-data-readers>=0.1.1; extra == "sinapsis-data-readers"
Provides-Extra: sinapsis-data-visualization
Requires-Dist: sinapsis-data-visualization[all]>=0.1.12; extra == "sinapsis-data-visualization"
Provides-Extra: sinapsis-data-writers
Requires-Dist: sinapsis-data-writers>=0.1.1; extra == "sinapsis-data-writers"
Provides-Extra: all
Requires-Dist: sinapsis-dfine[sinapsis-data-readers]; extra == "all"
Requires-Dist: sinapsis-dfine[sinapsis-data-visualization]; extra == "all"
Requires-Dist: sinapsis-dfine[sinapsis-data-writers]; extra == "all"
Dynamic: license-file
